.travis.yml
AUTHORS.md
CHANGELOG.md
CONTRIBUTING.md
LICENSE
MANIFEST.in
README.md
setup.cfg
setup.py
tox.ini
ci/bootstrap.py
src/.gitignore
src/paylense/__init__.py
src/paylense/__main__.py
src/paylense/cli.py
src/paylense/client.py
src/paylense/collections.py
src/paylense/config.py
src/paylense/disbursements.py
src/paylense/errors.py
src/paylense/utils.py
src/paylense_sdk.egg-info/PKG-INFO
src/paylense_sdk.egg-info/SOURCES.txt
src/paylense_sdk.egg-info/dependency_links.txt
src/paylense_sdk.egg-info/entry_points.txt
src/paylense_sdk.egg-info/not-zip-safe
src/paylense_sdk.egg-info/requires.txt
src/paylense_sdk.egg-info/top_level.txt
tests/__init__.py
tests/integration/test_collections.py
tests/integration/test_disbursements.py
tests/integration/features/collections.feature
tests/integration/features/disbursements.feature
tests/unitests/__init__.py
tests/unitests/test_collections.py
tests/unitests/test_disbursements.py
tests/unitests/utils.py