Metadata-Version: 2.1
Name: paylense-sdk
Version: 1.0.1
Summary: Python wrapper for the Winopay Paylense API.
Home-page: https://github.com/winopay/paylense-python-sdk
Author: Winopay
Author-email: acellam.guy@gmail.com
License: MIT license
Keywords: Paylense API,Paylense API Python Wrapper,Paylense API Python,Paylense API
Platform: UNKNOWN
Classifier: Development Status :: 5 - Production/Stable
Classifier: Intended Audience :: Developers
Classifier: License :: OSI Approved :: MIT License
Classifier: Operating System :: Unix
Classifier: Operating System :: POSIX
Classifier: Operating System :: Microsoft :: Windows
Classifier: Programming Language :: Python
Classifier: Programming Language :: Python :: 3
Classifier: Programming Language :: Python :: 3.4
Classifier: Programming Language :: Python :: 3.5
Classifier: Programming Language :: Python :: 3.6
Classifier: Programming Language :: Python :: 3.7
Classifier: Programming Language :: Python :: Implementation :: CPython
Classifier: Programming Language :: Python :: Implementation :: PyPy
Classifier: Topic :: Utilities
Provides-Extra: test
Provides-Extra: dev
